lemuria/__init__.py
lemuria/__main__.py
lemuria/device_command_handler.py
lemuria/protocol.py
lemuria/streaming_sequencer.py
lemuria/tcp_device.py
lemuria/udp_listener.py
lemuria/version.py
lemuria-2.0.0.dist-info/LICENSE.txt
lemuria-2.0.0.dist-info/METADATA
lemuria-2.0.0.dist-info/WHEEL
lemuria-2.0.0.dist-info/entry_points.txt
lemuria-2.0.0.dist-info/top_level.txt
lemuria-2.0.0.dist-info/RECORD
