Metadata-Version: 2.1
Name: lemuria
Version: 2.0.0
Summary: Application for replaying recorded Asphodel sensor data
Home-page: https://bitbucket.org/suprocktech/lemuria
Author: Suprock Technologies, LLC
Author-email: inquiries@suprocktech.com
License: UNKNOWN
Keywords: asphodel suprock apd
Platform: UNKNOWN
Classifier: Programming Language :: Python :: 3
Classifier: License :: OSI Approved :: ISC License (ISCL)
Classifier: Operating System :: OS Independent
Classifier: Topic :: System :: Hardware
Requires-Python: >=3.6
License-File: LICENSE.txt
Requires-Dist: asphodel (>=1.3.4)
